CHANGES.rst
CONTRIBUTORS.rst
DEVELOP.rst
DEVELOP_THEME.rst
LICENSE.GPL
LICENSE.rst
MANIFEST.in
README.md
README.rst
setup.cfg
setup.py
docs/LICENSE.GPL
docs/LICENSE.rst
docs/index.rst
src/ideabox/__init__.py
src/ideabox.diazotheme.spirit.egg-info/PKG-INFO
src/ideabox.diazotheme.spirit.egg-info/SOURCES.txt
src/ideabox.diazotheme.spirit.egg-info/dependency_links.txt
src/ideabox.diazotheme.spirit.egg-info/entry_points.txt
src/ideabox.diazotheme.spirit.egg-info/namespace_packages.txt
src/ideabox.diazotheme.spirit.egg-info/not-zip-safe
src/ideabox.diazotheme.spirit.egg-info/requires.txt
src/ideabox.diazotheme.spirit.egg-info/top_level.txt
src/ideabox/diazotheme/__init__.py
src/ideabox/diazotheme/spirit/__init__.py
src/ideabox/diazotheme/spirit/configure.zcml
src/ideabox/diazotheme/spirit/interfaces.py
src/ideabox/diazotheme/spirit/setuphandlers.py
src/ideabox/diazotheme/spirit/testing.py
src/ideabox/diazotheme/spirit/upgrades.py
src/ideabox/diazotheme/spirit/upgrades.zcml
src/ideabox/diazotheme/spirit/browser/__init__.py
src/ideabox/diazotheme/spirit/browser/configure.zcml
src/ideabox/diazotheme/spirit/browser/diazo.py
src/ideabox/diazotheme/spirit/browser/overrides/.gitkeep
src/ideabox/diazotheme/spirit/browser/static/.gitkeep
src/ideabox/diazotheme/spirit/locales/update.sh
src/ideabox/diazotheme/spirit/profiles/default/actions.xml
src/ideabox/diazotheme/spirit/profiles/default/browserlayer.xml
src/ideabox/diazotheme/spirit/profiles/default/metadata.xml
src/ideabox/diazotheme/spirit/profiles/default/registry.xml
src/ideabox/diazotheme/spirit/profiles/default/theme.xml
src/ideabox/diazotheme/spirit/profiles/uninstall/browserlayer.xml
src/ideabox/diazotheme/spirit/profiles/uninstall/theme.xml
src/ideabox/diazotheme/spirit/tests/__init__.py
src/ideabox/diazotheme/spirit/tests/test_robot.py
src/ideabox/diazotheme/spirit/tests/test_setup.py
src/ideabox/diazotheme/spirit/tests/robot/test_example.robot
src/ideabox/diazotheme/spirit/theme/backend.xml
src/ideabox/diazotheme/spirit/theme/barceloneta-apple-touch-icon-114x114-precomposed.png
src/ideabox/diazotheme/spirit/theme/barceloneta-apple-touch-icon-144x144-precomposed.png
src/ideabox/diazotheme/spirit/theme/barceloneta-apple-touch-icon-57x57-precomposed.png
src/ideabox/diazotheme/spirit/theme/barceloneta-apple-touch-icon-72x72-precomposed.png
src/ideabox/diazotheme/spirit/theme/barceloneta-apple-touch-icon-precomposed.png
