Metadata-Version: 2.1
Name: ideabox.diazotheme.spirit
Version: 1.2.8
Summary: Spirit theme for Ideabox
Home-page: https://pypi.python.org/pypi/ideabox.diazotheme.spirit
Author: maud gennart
Author-email: maud.gennart@imio.be
License: GPL version 2
Keywords: Python Plone
Platform: UNKNOWN
Classifier: Environment :: Web Environment
Classifier: Framework :: Plone
Classifier: Framework :: Plone :: 5.1
Classifier: Programming Language :: Python
Classifier: Programming Language :: Python :: 2.7
Classifier: Operating System :: OS Independent
Classifier: License :: OSI Approved :: GNU General Public License v2 (GPLv2)
Provides-Extra: test
